{"elements":{"nodes":[{"data":{"labels":["NiamObject","NiamNode","NiamAuthZObject"],"id":"664","name":"Document","x":1504.4853820800781,"y":265.7022247314453,"properties":{"name":"Document","description":null,"displayName":"Document","icon":"default.png","isSubject":null,"isAction":null,"isVC":null,"isHolder":null,"isIssuer":null,"isClaim":null,"isResource":null,"selfRegistration":false}}},{"data":{"labels":["NiamObject","NiamNode","NiamAuthZVC"],"id":"668","name":"VC","x":1147.5469970703125,"y":-73.91258716583252,"properties":{"name":"VC","description":null,"displayName":"VC","icon":"default.png","isSubject":null,"isAction":null,"isVC":null,"isHolder":null,"isIssuer":null,"isClaim":null,"isResource":null,"selfRegistration":false}}},{"data":{"labels":["NiamObject","NiamNode","NiamAuthZClaim"],"id":"666","name":"Claim","x":1061.8576965332031,"y":317.947322845459,"properties":{"name":"Claim","description":null,"displayName":"Claim","icon":"default.png","isSubject":null,"isAction":null,"isVC":null,"isHolder":null,"isIssuer":null,"isClaim":null,"isResource":null,"selfRegistration":false}}},{"data":{"labels":["NiamObject","NiamNode","NiamAuthZSubject"],"id":"663","name":"User","x":1089.345458984375,"y":-515.2077484130859,"properties":{"name":"User","description":null,"displayName":"User","icon":"default.png","isSubject":null,"isAction":null,"isVC":null,"isHolder":null,"isIssuer":null,"isClaim":null,"isResource":null,"selfRegistration":true}}},{"data":{"labels":["NiamObject","NiamNode","NiamAuthZIssuer"],"id":"667","name":"Issuer","x":1497.8526000976562,"y":-307.46974897384644,"properties":{"name":"Issuer","description":null,"displayName":"Issuer","icon":"default.png","isSubject":null,"isAction":null,"isVC":null,"isHolder":null,"isIssuer":null,"isClaim":null,"isResource":null,"selfRegistration":false}}},{"data":{"labels":["NiamObject","NiamNode"],"id":"665","name":"QRCode","x":443.02219009399414,"y":-427.84975814819336,"properties":{"name":"QRCode","description":null,"displayName":"QRCode","icon":"default.png","isSubject":null,"isAction":null,"isVC":null,"isHolder":null,"isIssuer":null,"isClaim":null,"isResource":null,"selfRegistration":false}}},{"data":{"labels":["NiamObject","NiamNode","NiamAuthZHolder"],"id":"669","name":"Holder","x":799.3440856933594,"y":-251.25167083740234,"properties":{"name":"Holder","description":null,"displayName":"Holder","icon":"default.png","isSubject":null,"isAction":null,"isVC":null,"isHolder":null,"isIssuer":null,"isClaim":null,"isResource":null,"selfRegistration":false}}},{"data":{"labels":["NiamField"],"id":"674","name":"DocInfo","x":null,"y":null,"properties":{"name":"DocInfo","displayName":"DocInfo","fieldType":"String","relatedTo":"c48db9f2-c61b-433b-8b49-ab5d2462b68e","relatedToName":"Document","isArray":false,"icon":"field-default.png","isRequired":false,"isNaming":false,"maxLength":0,"minLength":0,"relLabelName":null,"direction":null,"accessibleOnOppositeSide":null,"oppositeSideFieldName":null,"regex":null,"isUnique":null,"isDisplay":true,"customValidationFunc":null,"properties":null}}},{"data":{"labels":["NiamField"],"id":"675","name":"DocName","x":null,"y":null,"properties":{"name":"DocName","displayName":"DocName","fieldType":"String","relatedTo":"c48db9f2-c61b-433b-8b49-ab5d2462b68e","relatedToName":"Document","isArray":false,"icon":"field-default.png","isRequired":false,"isNaming":true,"maxLength":0,"minLength":0,"relLabelName":null,"direction":null,"accessibleOnOppositeSide":null,"oppositeSideFieldName":null,"regex":null,"isUnique":null,"isDisplay":false,"customValidationFunc":null,"properties":null}}},{"data":{"labels":["NiamField","NiamAuthZVC"],"id":"687","name":"VC_Type_Claim","x":null,"y":null,"properties":{"name":"VC_Type_Claim","displayName":"VC_Type","fieldType":"Relationship","relatedTo":"50fac7d0-aad0-4b87-be92-325b68c058e7","relatedToName":"Claim","isArray":false,"icon":"field-default.png","isRequired":false,"isNaming":false,"maxLength":0,"minLength":0,"relLabelName":null,"direction":"OUT","accessibleOnOppositeSide":false,"oppositeSideFieldName":null,"regex":null,"isUnique":null,"isDisplay":false,"customValidationFunc":null,"properties":null}}},{"data":{"labels":["NiamField"],"id":"685","name":"identifier","x":null,"y":null,"properties":{"name":"identifier","displayName":"identifier","fieldType":"String","relatedTo":"f139bbb9-4955-456b-b89e-98d951f37f93","relatedToName":"VC","isArray":false,"icon":"field-default.png","isRequired":false,"isNaming":true,"maxLength":0,"minLength":0,"relLabelName":null,"direction":null,"accessibleOnOppositeSide":null,"oppositeSideFieldName":null,"regex":null,"isUnique":null,"isDisplay":false,"customValidationFunc":null,"properties":null}}},{"data":{"labels":["NiamField","NiamAuthZVC"],"id":"686","name":"EmployeeID_Claim","x":null,"y":null,"properties":{"name":"EmployeeID_Claim","displayName":"EmployeeID","fieldType":"Relationship","relatedTo":"50fac7d0-aad0-4b87-be92-325b68c058e7","relatedToName":"Claim","isArray":false,"icon":"field-default.png","isRequired":false,"isNaming":false,"maxLength":0,"minLength":0,"relLabelName":null,"direction":"OUT","accessibleOnOppositeSide":false,"oppositeSideFieldName":null,"regex":null,"isUnique":null,"isDisplay":false,"customValidationFunc":null,"properties":null}}},{"data":{"labels":["NiamField"],"id":"681","name":"value","x":null,"y":null,"properties":{"name":"value","displayName":"value","fieldType":"String","relatedTo":"50fac7d0-aad0-4b87-be92-325b68c058e7","relatedToName":"Claim","isArray":false,"icon":"field-default.png","isRequired":false,"isNaming":false,"maxLength":0,"minLength":0,"relLabelName":null,"direction":null,"accessibleOnOppositeSide":null,"oppositeSideFieldName":null,"regex":null,"isUnique":null,"isDisplay":true,"customValidationFunc":null,"properties":null}}},{"data":{"labels":["NiamField"],"id":"680","name":"CAN_ACCESS_Document","x":null,"y":null,"properties":{"name":"CAN_ACCESS_Document","displayName":"CAN_ACCESS","fieldType":"Relationship","relatedTo":"c48db9f2-c61b-433b-8b49-ab5d2462b68e","relatedToName":"Document","isArray":false,"icon":"field-default.png","isRequired":false,"isNaming":false,"maxLength":0,"minLength":0,"relLabelName":null,"direction":"OUT","accessibleOnOppositeSide":false,"oppositeSideFieldName":null,"regex":null,"isUnique":null,"isDisplay":false,"customValidationFunc":null,"properties":null}}},{"data":{"labels":["NiamField"],"id":"673","name":"WORKS_FOR_Issuer","x":null,"y":null,"properties":{"name":"WORKS_FOR_Issuer","displayName":"WORKS_FOR","fieldType":"Relationship","relatedTo":"0551d86e-7676-4095-a901-a9831385126b","relatedToName":"Issuer","isArray":false,"icon":"field-default.png","isRequired":false,"isNaming":false,"maxLength":0,"minLength":0,"relLabelName":null,"direction":"OUT","accessibleOnOppositeSide":false,"oppositeSideFieldName":null,"regex":null,"isUnique":null,"isDisplay":false,"customValidationFunc":null,"properties":null}}},{"data":{"labels":["NiamField"],"id":"672","name":"username","x":null,"y":null,"properties":{"name":"username","displayName":"username","fieldType":"String","relatedTo":"7f315960-28c6-4a07-a284-33c2cc053699","relatedToName":"User","isArray":false,"icon":"field-default.png","isRequired":false,"isNaming":true,"maxLength":0,"minLength":0,"relLabelName":null,"direction":null,"accessibleOnOppositeSide":null,"oppositeSideFieldName":null,"regex":null,"isUnique":null,"isDisplay":false,"customValidationFunc":null,"properties":null}}},{"data":{"labels":["NiamField"],"id":"670","name":"IS_Holder","x":null,"y":null,"properties":{"name":"IS_Holder","displayName":"IS","fieldType":"Relationship","relatedTo":"c757f191-19f7-46d2-a1c4-d38db1472ee4","relatedToName":"Holder","isArray":false,"icon":"field-default.png","isRequired":false,"isNaming":false,"maxLength":0,"minLength":0,"relLabelName":null,"direction":"OUT","accessibleOnOppositeSide":false,"oppositeSideFieldName":null,"regex":null,"isUnique":null,"isDisplay":false,"customValidationFunc":null,"properties":null}}},{"data":{"labels":["NiamField"],"id":"671","name":"password","x":null,"y":null,"properties":{"name":"password","displayName":"password","fieldType":"String","relatedTo":"7f315960-28c6-4a07-a284-33c2cc053699","relatedToName":"User","isArray":false,"icon":"field-default.png","isRequired":false,"isNaming":false,"maxLength":0,"minLength":0,"relLabelName":null,"direction":null,"accessibleOnOppositeSide":null,"oppositeSideFieldName":null,"regex":null,"isUnique":null,"isDisplay":false,"customValidationFunc":null,"properties":null}}},{"data":{"labels":["NiamField"],"id":"684","name":"identifier","x":null,"y":null,"properties":{"name":"identifier","displayName":"identifier","fieldType":"String","relatedTo":"0551d86e-7676-4095-a901-a9831385126b","relatedToName":"Issuer","isArray":false,"icon":"field-default.png","isRequired":false,"isNaming":true,"maxLength":0,"minLength":0,"relLabelName":null,"direction":null,"accessibleOnOppositeSide":null,"oppositeSideFieldName":null,"regex":null,"isUnique":null,"isDisplay":false,"customValidationFunc":null,"properties":null}}},{"data":{"labels":["NiamField","NiamAuthZVC"],"id":"683","name":"url_Claim","x":null,"y":null,"properties":{"name":"url_Claim","displayName":"url","fieldType":"Relationship","relatedTo":"50fac7d0-aad0-4b87-be92-325b68c058e7","relatedToName":"Claim","isArray":false,"icon":"field-default.png","isRequired":false,"isNaming":false,"maxLength":0,"minLength":0,"relLabelName":null,"direction":"OUT","accessibleOnOppositeSide":false,"oppositeSideFieldName":null,"regex":null,"isUnique":null,"isDisplay":false,"customValidationFunc":null,"properties":null}}},{"data":{"labels":["NiamField"],"id":"682","name":"ISSUES_VC","x":null,"y":null,"properties":{"name":"ISSUES_VC","displayName":"ISSUES","fieldType":"Relationship","relatedTo":"f139bbb9-4955-456b-b89e-98d951f37f93","relatedToName":"VC","isArray":false,"icon":"field-default.png","isRequired":false,"isNaming":false,"maxLength":0,"minLength":0,"relLabelName":null,"direction":"OUT","accessibleOnOppositeSide":false,"oppositeSideFieldName":null,"regex":null,"isUnique":null,"isDisplay":false,"customValidationFunc":null,"properties":null}}},{"data":{"labels":["NiamField"],"id":"679","name":"QRImage","x":null,"y":null,"properties":{"name":"QRImage","displayName":"QRImage","fieldType":"String","relatedTo":"e2d1e4ff-6c0a-4f5f-830d-a06ee7f45c28","relatedToName":"QRCode","isArray":false,"icon":"field-default.png","isRequired":false,"isNaming":false,"maxLength":0,"minLength":0,"relLabelName":null,"direction":null,"accessibleOnOppositeSide":null,"oppositeSideFieldName":null,"regex":null,"isUnique":null,"isDisplay":false,"customValidationFunc":null,"properties":null}}},{"data":{"labels":["NiamField"],"id":"676","name":"QRID","x":null,"y":null,"properties":{"name":"QRID","displayName":"QRID","fieldType":"String","relatedTo":"e2d1e4ff-6c0a-4f5f-830d-a06ee7f45c28","relatedToName":"QRCode","isArray":false,"icon":"field-default.png","isRequired":false,"isNaming":true,"maxLength":0,"minLength":0,"relLabelName":null,"direction":null,"accessibleOnOppositeSide":null,"oppositeSideFieldName":null,"regex":null,"isUnique":null,"isDisplay":false,"customValidationFunc":null,"properties":null}}},{"data":{"labels":["NiamField"],"id":"677","name":"VCClaimsData","x":null,"y":null,"properties":{"name":"VCClaimsData","displayName":"VCClaimsData","fieldType":"String","relatedTo":"e2d1e4ff-6c0a-4f5f-830d-a06ee7f45c28","relatedToName":"QRCode","isArray":false,"icon":"field-default.png","isRequired":false,"isNaming":false,"maxLength":0,"minLength":0,"relLabelName":null,"direction":null,"accessibleOnOppositeSide":null,"oppositeSideFieldName":null,"regex":null,"isUnique":null,"isDisplay":false,"customValidationFunc":null,"properties":null}}},{"data":{"labels":["NiamField"],"id":"689","name":"CAN_CLAIM_QRCode","x":null,"y":null,"properties":{"name":"CAN_CLAIM_QRCode","displayName":"CAN_CLAIM","fieldType":"Relationship","relatedTo":"e2d1e4ff-6c0a-4f5f-830d-a06ee7f45c28","relatedToName":"QRCode","isArray":false,"icon":"field-default.png","isRequired":false,"isNaming":false,"maxLength":0,"minLength":0,"relLabelName":null,"direction":"OUT","accessibleOnOppositeSide":false,"oppositeSideFieldName":null,"regex":null,"isUnique":null,"isDisplay":false,"customValidationFunc":null,"properties":null}}},{"data":{"labels":["NiamField"],"id":"690","name":"identifier","x":null,"y":null,"properties":{"name":"identifier","displayName":"identifier","fieldType":"String","relatedTo":"c757f191-19f7-46d2-a1c4-d38db1472ee4","relatedToName":"Holder","isArray":false,"icon":"field-default.png","isRequired":false,"isNaming":true,"maxLength":0,"minLength":0,"relLabelName":null,"direction":null,"accessibleOnOppositeSide":null,"oppositeSideFieldName":null,"regex":null,"isUnique":null,"isDisplay":false,"customValidationFunc":null,"properties":null}}},{"data":{"labels":["NiamField"],"id":"692","name":"HOLDS_VC","x":null,"y":null,"properties":{"name":"HOLDS_VC","displayName":"HOLDS","fieldType":"Relationship","relatedTo":"f139bbb9-4955-456b-b89e-98d951f37f93","relatedToName":"VC","isArray":false,"icon":"field-default.png","isRequired":false,"isNaming":false,"maxLength":0,"minLength":0,"relLabelName":null,"direction":"OUT","accessibleOnOppositeSide":false,"oppositeSideFieldName":null,"regex":null,"isUnique":null,"isDisplay":false,"customValidationFunc":null,"properties":null}}},{"data":{"labels":["NiamField","NiamAuthZVC"],"id":"688","name":"email_Claim","x":null,"y":null,"properties":{"name":"email_Claim","displayName":"email","fieldType":"Relationship","relatedTo":"50fac7d0-aad0-4b87-be92-325b68c058e7","relatedToName":"Claim","isArray":false,"icon":"field-default.png","isRequired":false,"isNaming":false,"maxLength":0,"minLength":0,"relLabelName":null,"direction":"OUT","accessibleOnOppositeSide":false,"oppositeSideFieldName":null,"regex":null,"isUnique":null,"isDisplay":false,"customValidationFunc":null,"properties":null}}},{"data":{"labels":["NiamField"],"id":"691","name":"WORKS_FOR_Issuer","x":null,"y":null,"properties":{"name":"WORKS_FOR_Issuer","displayName":"WORKS_FOR","fieldType":"Relationship","relatedTo":"0551d86e-7676-4095-a901-a9831385126b","relatedToName":"Issuer","isArray":false,"icon":"field-default.png","isRequired":false,"isNaming":false,"maxLength":0,"minLength":0,"relLabelName":null,"direction":"OUT","accessibleOnOppositeSide":false,"oppositeSideFieldName":null,"regex":null,"isUnique":null,"isDisplay":false,"customValidationFunc":null,"properties":null}}},{"data":{"labels":["NiamScript","NiamNode"],"id":"693","name":"hashPwd","x":1535.1691284179688,"y":-590.5765686035156,"properties":{"name":"hashPwd","displayName":"hashPwd","returnType":null,"funcName":"hashPwd","scriptText":"b2JqZWN0LnBhc3N3b3JkPU5pYW1TZXJ2aWNlLmhhc2hQYXNzd29yZEZ1bmMob2JqZWN0LnBhc3N3b3JkKQ=="}}}],"edges":[{"data":{"source":"668","target":"666","name":"NIAM_AUTHZ_PATH","id":"583-edge","properties":{"name":"AuthPath","displayName":"AuthPath","relatedTo":"686","fieldType":null,"eventType":null}}},{"data":{"source":"666","target":"664","name":"NIAM_AUTHZ_PATH","id":"582-edge","properties":{"name":"AuthPath","displayName":"AuthPath","relatedTo":"680","fieldType":null,"eventType":null}}},{"data":{"source":"663","target":"669","name":"NIAM_AUTHZ_PATH","id":"581-edge","properties":{"name":"AuthPath","displayName":"AuthPath","relatedTo":"670","fieldType":null,"eventType":null}}},{"data":{"source":"669","target":"668","name":"NIAM_AUTHZ_PATH","id":"584-edge","properties":{"name":"AuthPath","displayName":"AuthPath","relatedTo":"692","fieldType":null,"eventType":null}}},{"data":{"source":"664","target":"674","name":"HAS_NIAM_FIELD","id":"592-edge"}},{"data":{"source":"664","target":"675","name":"HAS_NIAM_FIELD","id":"593-edge"}},{"data":{"source":"668","target":"687","name":"HAS_NIAM_FIELD","id":"610-edge"}},{"data":{"source":"668","target":"685","name":"HAS_NIAM_FIELD","id":"607-edge"}},{"data":{"source":"668","target":"686","name":"HAS_NIAM_FIELD","id":"608-edge"}},{"data":{"source":"666","target":"681","name":"HAS_NIAM_FIELD","id":"600-edge"}},{"data":{"source":"666","target":"680","name":"HAS_NIAM_FIELD","id":"598-edge"}},{"data":{"source":"663","target":"673","name":"HAS_NIAM_FIELD","id":"591-edge"}},{"data":{"source":"663","target":"672","name":"HAS_NIAM_FIELD","id":"587-edge"}},{"data":{"source":"663","target":"670","name":"HAS_NIAM_FIELD","id":"585-edge"}},{"data":{"source":"663","target":"671","name":"HAS_NIAM_FIELD","id":"586-edge"}},{"data":{"source":"667","target":"684","name":"HAS_NIAM_FIELD","id":"605-edge"}},{"data":{"source":"667","target":"683","name":"HAS_NIAM_FIELD","id":"604-edge"}},{"data":{"source":"667","target":"682","name":"HAS_NIAM_FIELD","id":"601-edge"}},{"data":{"source":"665","target":"679","name":"HAS_NIAM_FIELD","id":"596-edge"}},{"data":{"source":"665","target":"676","name":"HAS_NIAM_FIELD","id":"594-edge"}},{"data":{"source":"665","target":"677","name":"HAS_NIAM_FIELD","id":"595-edge"}},{"data":{"source":"669","target":"689","name":"HAS_NIAM_FIELD","id":"612-edge"}},{"data":{"source":"669","target":"690","name":"HAS_NIAM_FIELD","id":"613-edge"}},{"data":{"source":"669","target":"692","name":"HAS_NIAM_FIELD","id":"616-edge"}},{"data":{"source":"669","target":"688","name":"HAS_NIAM_FIELD","id":"611-edge"}},{"data":{"source":"669","target":"691","name":"HAS_NIAM_FIELD","id":"615-edge"}},{"data":{"source":"664","target":"675","name":"NIAM_HAS_NAMING_FIELD","id":"623-edge"}},{"data":{"source":"668","target":"685","name":"NIAM_HAS_NAMING_FIELD","id":"630-edge"}},{"data":{"source":"663","target":"672","name":"NIAM_HAS_NAMING_FIELD","id":"619-edge"}},{"data":{"source":"667","target":"684","name":"NIAM_HAS_NAMING_FIELD","id":"628-edge"}},{"data":{"source":"665","target":"676","name":"NIAM_HAS_NAMING_FIELD","id":"624-edge"}},{"data":{"source":"669","target":"690","name":"NIAM_HAS_NAMING_FIELD","id":"631-edge"}},{"data":{"source":"674","target":"664","name":"RELATED_TO_NIAM_NODE","id":"644-edge"}},{"data":{"source":"675","target":"664","name":"RELATED_TO_NIAM_NODE","id":"647-edge"}},{"data":{"source":"687","target":"666","name":"RELATED_TO_NIAM_NODE","id":"659-edge"}},{"data":{"source":"685","target":"668","name":"RELATED_TO_NIAM_NODE","id":"657-edge"}},{"data":{"source":"686","target":"666","name":"RELATED_TO_NIAM_NODE","id":"658-edge"}},{"data":{"source":"681","target":"666","name":"RELATED_TO_NIAM_NODE","id":"653-edge"}},{"data":{"source":"680","target":"664","name":"RELATED_TO_NIAM_NODE","id":"652-edge"}},{"data":{"source":"673","target":"667","name":"RELATED_TO_NIAM_NODE","id":"642-edge"}},{"data":{"source":"672","target":"663","name":"RELATED_TO_NIAM_NODE","id":"641-edge"}},{"data":{"source":"670","target":"669","name":"RELATED_TO_NIAM_NODE","id":"632-edge"}},{"data":{"source":"671","target":"663","name":"RELATED_TO_NIAM_NODE","id":"640-edge"}},{"data":{"source":"684","target":"667","name":"RELATED_TO_NIAM_NODE","id":"656-edge"}},{"data":{"source":"683","target":"666","name":"RELATED_TO_NIAM_NODE","id":"655-edge"}},{"data":{"source":"682","target":"668","name":"RELATED_TO_NIAM_NODE","id":"654-edge"}},{"data":{"source":"679","target":"665","name":"RELATED_TO_NIAM_NODE","id":"651-edge"}},{"data":{"source":"676","target":"665","name":"RELATED_TO_NIAM_NODE","id":"648-edge"}},{"data":{"source":"677","target":"665","name":"RELATED_TO_NIAM_NODE","id":"650-edge"}},{"data":{"source":"689","target":"665","name":"RELATED_TO_NIAM_NODE","id":"661-edge"}},{"data":{"source":"690","target":"669","name":"RELATED_TO_NIAM_NODE","id":"662-edge"}},{"data":{"source":"692","target":"668","name":"RELATED_TO_NIAM_NODE","id":"664-edge"}},{"data":{"source":"688","target":"666","name":"RELATED_TO_NIAM_NODE","id":"660-edge"}},{"data":{"source":"691","target":"667","name":"RELATED_TO_NIAM_NODE","id":"663-edge"}},{"data":{"source":"693","target":"663","name":"NIAM_APPLIES_TO","id":"665-edge","properties":{"name":"hashPwd","displayName":"hashPwd","relatedTo":"7f315960-28c6-4a07-a284-33c2cc053699","fieldType":"Relationship","eventType":"onCreate"}}}]}}